{
	"fade-in": [
		{
			"sectionTitle": "Cool beans",
			"sectionImage": "https://oanapatran.com/images/91d8fd12-5c2f-43aa-8e4b-b35a0fbe05f4",
			"sectionContent": "Something cool"
		},
		{
			"sectionTitle": "Oana Patran",
			"sectionImage": "oana-portrait.jpg",
			"sectionContent": "Oana Patran is a multifaceted artist, healer, and dancer hailing from Romania and currently based in Chicago. As a modern-day witch, she combines her diverse talents to create transformative experiences and art that speaks to the soul.\n\nDrawing from her rich cultural heritage and spiritual practices, Oana's work spans multiple disciplines, each infused with her unique energy and vision."
		}
	],
	"main-section": [
		{
			"sectionTitle": "Hello",
			"sectionContent": "\n          "
		}
	]
}